[
  {
    "id": "bwp-BW01",
    "name": "Snivy",
    "setName": "BW Black Star Promos",
    "number": "BW01",
    "rarity": "Promo",
    "artist": "Ken Sugimori",
    "imageUrl": "https://images.pokemontcg.io/bwp/BW01_hires.png"
  },
  {
    "id": "bwp-BW02",
    "name": "Tepig",
    "setName": "BW Black Star Promos",
    "number": "BW02",
    "rarity": "Promo",
    "artist": "Ken Sugimori",
    "imageUrl": "https://images.pokemontcg.io/bwp/BW02_hires.png"
  },
  {
    "id": "bwp-BW03",
    "name": "Oshawott",
    "setName": "BW Black Star Promos",
    "number": "BW03",
    "rarity": "Promo",
    "artist": "Ken Sugimori",
    "imageUrl": "https://images.pokemontcg.io/bwp/BW03_hires.png"
  },
  {
    "id": "bwp-BW004",
    "name": "Reshiram",
    "setName": "BW Black Star Promos",
    "number": "BW004",
    "rarity": "Promo",
    "artist": "5ban Graphics",
    "imageUrl": "https://images.pokemontcg.io/bwp/BW004_hires.png"
  },
  {
    "id": "bwp-BW005",
    "name": "Zekrom",
    "setName": "BW Black Star Promos",
    "number": "BW005",
    "rarity": "Promo",
    "artist": "5ban Graphics",
    "imageUrl": "https://images.pokemontcg.io/bwp/BW005_hires.png"
  },
  {
    "id": "bwp-BW06",
    "name": "Snivy",
    "setName": "BW Black Star Promos",
    "number": "BW06",
    "rarity": "Promo",
    "artist": "Shizurow",
    "imageUrl": "https://images.pokemontcg.io/bwp/BW06_hires.png"
  },
  {
    "id": "bwp-BW07",
    "name": "Tepig",
    "setName": "BW Black Star Promos",
    "number": "BW07",
    "rarity": "Promo",
    "artist": "Shin Nagasawa",
    "imageUrl": "https://images.pokemontcg.io/bwp/BW07_hires.png"
  },
  {
    "id": "bwp-BW08",
    "name": "Oshawott",
    "setName": "BW Black Star Promos",
    "number": "BW08",
    "rarity": "Promo",
    "artist": "Mitsuhiro Arita",
    "imageUrl": "https://images.pokemontcg.io/bwp/BW08_hires.png"
  },
  {
    "id": "bwp-BW09",
    "name": "Zoroark",
    "setName": "BW Black Star Promos",
    "number": "BW09",
    "rarity": "Promo",
    "artist": "Naoki Saito",
    "imageUrl": "https://images.pokemontcg.io/bwp/BW09_hires.png"
  },
  {
    "id": "bwp-BW10",
    "name": "Axew",
    "setName": "BW Black Star Promos",
    "number": "BW10",
    "rarity": "Promo",
    "artist": "Masakazu Fukuda",
    "imageUrl": "https://images.pokemontcg.io/bwp/BW10_hires.png"
  },
  {
    "id": "bwp-BW11",
    "name": "Pansage",
    "setName": "BW Black Star Promos",
    "number": "BW11",
    "rarity": "Promo",
    "artist": "Akira Komayama",
    "imageUrl": "https://images.pokemontcg.io/bwp/BW11_hires.png"
  },
  {
    "id": "bwp-BW12",
    "name": "Zorua",
    "setName": "BW Black Star Promos",
    "number": "BW12",
    "rarity": "Promo",
    "artist": "Tomokazu Komiya",
    "imageUrl": "https://images.pokemontcg.io/bwp/BW12_hires.png"
  },
  {
    "id": "bwp-BW13",
    "name": "Minccino",
    "setName": "BW Black Star Promos",
    "number": "BW13",
    "rarity": "Promo",
    "artist": "Atsuko Nishida",
    "imageUrl": "https://images.pokemontcg.io/bwp/BW13_hires.png"
  },
  {
    "id": "bwp-BW14",
    "name": "Pansage",
    "setName": "BW Black Star Promos",
    "number": "BW14",
    "rarity": "Promo",
    "artist": "Akira Komayama",
    "imageUrl": "https://images.pokemontcg.io/bwp/BW14_hires.png"
  },
  {
    "id": "bwp-BW15",
    "name": "Pidove",
    "setName": "BW Black Star Promos",
    "number": "BW15",
    "rarity": "Promo",
    "artist": "Naoki Saito",
    "imageUrl": "https://images.pokemontcg.io/bwp/BW15_hires.png"
  },
  {
    "id": "bwp-BW16",
    "name": "Axew",
    "setName": "BW Black Star Promos",
    "number": "BW16",
    "rarity": "Promo",
    "artist": "Masakazu Fukuda",
    "imageUrl": "https://images.pokemontcg.io/bwp/BW16_hires.png"
  },
  {
    "id": "bwp-BW17",
    "name": "Ducklett",
    "setName": "BW Black Star Promos",
    "number": "BW17",
    "rarity": "Promo",
    "artist": "Kagemaru Himeno",
    "imageUrl": "https://images.pokemontcg.io/bwp/BW17_hires.png"
  },
  {
    "id": "bwp-BW18",
    "name": "Darumaka",
    "setName": "BW Black Star Promos",
    "number": "BW18",
    "rarity": "Promo",
    "artist": "Akira Komayama",
    "imageUrl": "https://images.pokemontcg.io/bwp/BW18_hires.png"
  },
  {
    "id": "bwp-BW19",
    "name": "Zoroark",
    "setName": "BW Black Star Promos",
    "number": "BW19",
    "rarity": "Promo",
    "artist": "5ban Graphics",
    "imageUrl": "https://images.pokemontcg.io/bwp/BW19_hires.png"
  },
  {
    "id": "bwp-BW20",
    "name": "Serperior",
    "setName": "BW Black Star Promos",
    "number": "BW20",
    "rarity": "Promo",
    "artist": "5ban Graphics",
    "imageUrl": "https://images.pokemontcg.io/bwp/BW20_hires.png"
  },
  {
    "id": "bwp-BW21",
    "name": "Emboar",
    "setName": "BW Black Star Promos",
    "number": "BW21",
    "rarity": "Promo",
    "artist": "5ban Graphics",
    "imageUrl": "https://images.pokemontcg.io/bwp/BW21_hires.png"
  },
  {
    "id": "bwp-BW22",
    "name": "Samurott",
    "setName": "BW Black Star Promos",
    "number": "BW22",
    "rarity": "Promo",
    "artist": "5ban Graphics",
    "imageUrl": "https://images.pokemontcg.io/bwp/BW22_hires.png"
  },
  {
    "id": "bwp-BW23",
    "name": "Reshiram",
    "setName": "BW Black Star Promos",
    "number": "BW23",
    "rarity": "Promo",
    "artist": "5ban Graphics",
    "imageUrl": "https://images.pokemontcg.io/bwp/BW23_hires.png"
  },
  {
    "id": "bwp-BW24",
    "name": "Zekrom",
    "setName": "BW Black Star Promos",
    "number": "BW24",
    "rarity": "Promo",
    "artist": "5ban Graphics",
    "imageUrl": "https://images.pokemontcg.io/bwp/BW24_hires.png"
  },
  {
    "id": "bwp-BW25",
    "name": "Scraggy",
    "setName": "BW Black Star Promos",
    "number": "BW25",
    "rarity": "Promo",
    "artist": "Akira Komayama",
    "imageUrl": "https://images.pokemontcg.io/bwp/BW25_hires.png"
  },
  {
    "id": "bwp-BW26",
    "name": "Axew",
    "setName": "BW Black Star Promos",
    "number": "BW26",
    "rarity": "Promo",
    "artist": "Akira Komayama",
    "imageUrl": "https://images.pokemontcg.io/bwp/BW26_hires.png"
  },
  {
    "id": "bwp-BW27",
    "name": "Litwick",
    "setName": "BW Black Star Promos",
    "number": "BW27",
    "rarity": "Promo",
    "artist": "Atsuko Nishida",
    "imageUrl": "https://images.pokemontcg.io/bwp/BW27_hires.png"
  },
  {
    "id": "bwp-BW28",
    "name": "Tropical Beach",
    "setName": "BW Black Star Promos",
    "number": "BW28",
    "rarity": "Promo",
    "artist": "Naoki Saito",
    "imageUrl": "https://images.pokemontcg.io/bwp/BW28_hires.png"
  },
  {
    "id": "bwp-BW29",
    "name": "Victory Cup",
    "setName": "BW Black Star Promos",
    "number": "BW29",
    "rarity": "Promo",
    "artist": "5ban Graphics",
    "imageUrl": "https://images.pokemontcg.io/bwp/BW29_hires.png"
  },
  {
    "id": "bwp-BW30",
    "name": "Victory Cup",
    "setName": "BW Black Star Promos",
    "number": "BW30",
    "rarity": "Promo",
    "artist": "5ban Graphics",
    "imageUrl": "https://images.pokemontcg.io/bwp/BW30_hires.png"
  },
  {
    "id": "bwp-BW31",
    "name": "Victory Cup",
    "setName": "BW Black Star Promos",
    "number": "BW31",
    "rarity": "Promo",
    "artist": "5ban Graphics",
    "imageUrl": "https://images.pokemontcg.io/bwp/BW31_hires.png"
  },
  {
    "id": "bwp-BW32",
    "name": "Victini",
    "setName": "BW Black Star Promos",
    "number": "BW32",
    "rarity": "Promo",
    "artist": "5ban Graphics",
    "imageUrl": "https://images.pokemontcg.io/bwp/BW32_hires.png"
  },
  {
    "id": "bwp-BW33",
    "name": "Riolu",
    "setName": "BW Black Star Promos",
    "number": "BW33",
    "rarity": "Promo",
    "artist": "sui",
    "imageUrl": "https://images.pokemontcg.io/bwp/BW33_hires.png"
  },
  {
    "id": "bwp-BW34",
    "name": "Luxio",
    "setName": "BW Black Star Promos",
    "number": "BW34",
    "rarity": "Promo",
    "artist": "Naoki Saito",
    "imageUrl": "https://images.pokemontcg.io/bwp/BW34_hires.png"
  },
  {
    "id": "bwp-BW35",
    "name": "Meowth",
    "setName": "BW Black Star Promos",
    "number": "BW35",
    "rarity": "Promo",
    "artist": "Sumiyoshi Kizuki",
    "imageUrl": "https://images.pokemontcg.io/bwp/BW35_hires.png"
  },
  {
    "id": "bwp-BW36",
    "name": "Reshiram-EX",
    "setName": "BW Black Star Promos",
    "number": "BW36",
    "rarity": "Promo",
    "artist": "Shizurow",
    "imageUrl": "https://images.pokemontcg.io/bwp/BW36_hires.png"
  },
  {
    "id": "bwp-BW37",
    "name": "Kyurem-EX",
    "setName": "BW Black Star Promos",
    "number": "BW37",
    "rarity": "Promo",
    "artist": "Shizurow",
    "imageUrl": "https://images.pokemontcg.io/bwp/BW37_hires.png"
  },
  {
    "id": "bwp-BW38",
    "name": "Zekrom-EX",
    "setName": "BW Black Star Promos",
    "number": "BW38",
    "rarity": "Promo",
    "artist": "Shizurow",
    "imageUrl": "https://images.pokemontcg.io/bwp/BW38_hires.png"
  },
  {
    "id": "bwp-BW39",
    "name": "Battle City",
    "setName": "BW Black Star Promos",
    "number": "BW39",
    "rarity": "Promo",
    "artist": "Hideaki Hakozaki",
    "imageUrl": "https://images.pokemontcg.io/bwp/BW39_hires.png"
  },
  {
    "id": "bwp-BW40",
    "name": "Volcarona",
    "setName": "BW Black Star Promos",
    "number": "BW40",
    "rarity": "Promo",
    "artist": "Shin Nagasawa",
    "imageUrl": "https://images.pokemontcg.io/bwp/BW40_hires.png"
  },
  {
    "id": "bwp-BW41",
    "name": "Thundurus",
    "setName": "BW Black Star Promos",
    "number": "BW41",
    "rarity": "Promo",
    "artist": "5ban Graphics",
    "imageUrl": "https://images.pokemontcg.io/bwp/BW41_hires.png"
  },
  {
    "id": "bwp-BW42",
    "name": "Tornadus",
    "setName": "BW Black Star Promos",
    "number": "BW42",
    "rarity": "Promo",
    "artist": "5ban Graphics",
    "imageUrl": "https://images.pokemontcg.io/bwp/BW42_hires.png"
  },
  {
    "id": "bwp-BW43",
    "name": "Landorus",
    "setName": "BW Black Star Promos",
    "number": "BW43",
    "rarity": "Promo",
    "artist": "5ban Graphics",
    "imageUrl": "https://images.pokemontcg.io/bwp/BW43_hires.png"
  },
  {
    "id": "bwp-BW44",
    "name": "Kyurem",
    "setName": "BW Black Star Promos",
    "number": "BW44",
    "rarity": "Promo",
    "artist": "5ban Graphics",
    "imageUrl": "https://images.pokemontcg.io/bwp/BW44_hires.png"
  },
  {
    "id": "bwp-BW45",
    "name": "Mewtwo-EX",
    "setName": "BW Black Star Promos",
    "number": "BW45",
    "rarity": "Promo",
    "artist": "Toyste Beach",
    "imageUrl": "https://images.pokemontcg.io/bwp/BW45_hires.png"
  },
  {
    "id": "bwp-BW46",
    "name": "Darkrai-EX",
    "setName": "BW Black Star Promos",
    "number": "BW46",
    "rarity": "Promo",
    "artist": "Toyste Beach",
    "imageUrl": "https://images.pokemontcg.io/bwp/BW46_hires.png"
  },
  {
    "id": "bwp-BW47",
    "name": "Rayquaza-EX",
    "setName": "BW Black Star Promos",
    "number": "BW47",
    "rarity": "Promo",
    "artist": "Eske Yoshinob",
    "imageUrl": "https://images.pokemontcg.io/bwp/BW47_hires.png"
  },
  {
    "id": "bwp-BW48",
    "name": "Altaria",
    "setName": "BW Black Star Promos",
    "number": "BW48",
    "rarity": "Promo",
    "artist": "HiRON",
    "imageUrl": "https://images.pokemontcg.io/bwp/BW48_hires.png"
  },
  {
    "id": "bwp-BW49",
    "name": "Lilligant",
    "setName": "BW Black Star Promos",
    "number": "BW49",
    "rarity": "Promo",
    "artist": "Naoki Saito",
    "imageUrl": "https://images.pokemontcg.io/bwp/BW49_hires.png"
  },
  {
    "id": "bwp-BW50",
    "name": "Tropical Beach",
    "setName": "BW Black Star Promos",
    "number": "BW50",
    "rarity": "Promo",
    "artist": "Naoki Saito",
    "imageUrl": "https://images.pokemontcg.io/bwp/BW50_hires.png"
  },
  {
    "id": "bwp-BW51",
    "name": "Crobat",
    "setName": "BW Black Star Promos",
    "number": "BW51",
    "rarity": "Promo",
    "artist": "5ban Graphics",
    "imageUrl": "https://images.pokemontcg.io/bwp/BW51_hires.png"
  },
  {
    "id": "bwp-BW52",
    "name": "Lillipup",
    "setName": "BW Black Star Promos",
    "number": "BW52",
    "rarity": "Promo",
    "artist": "Mizue",
    "imageUrl": "https://images.pokemontcg.io/bwp/BW52_hires.png"
  },
  {
    "id": "bwp-BW53",
    "name": "Flygon",
    "setName": "BW Black Star Promos",
    "number": "BW53",
    "rarity": "Promo",
    "artist": "BERUBURI",
    "imageUrl": "https://images.pokemontcg.io/bwp/BW53_hires.png"
  },
  {
    "id": "bwp-BW54",
    "name": "Pikachu",
    "setName": "BW Black Star Promos",
    "number": "BW54",
    "rarity": "Promo",
    "artist": "5ban Graphics",
    "imageUrl": "https://images.pokemontcg.io/bwp/BW54_hires.png"
  },
  {
    "id": "bwp-BW55",
    "name": "Elgyem",
    "setName": "BW Black Star Promos",
    "number": "BW55",
    "rarity": "Promo",
    "artist": "Mizue",
    "imageUrl": "https://images.pokemontcg.io/bwp/BW55_hires.png"
  },
  {
    "id": "bwp-BW56",
    "name": "Empoleon",
    "setName": "BW Black Star Promos",
    "number": "BW56",
    "rarity": "Promo",
    "artist": "Shin Nagasawa",
    "imageUrl": "https://images.pokemontcg.io/bwp/BW56_hires.png"
  },
  {
    "id": "bwp-BW57",
    "name": "Haxorus",
    "setName": "BW Black Star Promos",
    "number": "BW57",
    "rarity": "Promo",
    "artist": "kawayoo",
    "imageUrl": "https://images.pokemontcg.io/bwp/BW57_hires.png"
  },
  {
    "id": "bwp-BW58",
    "name": "Black Kyurem",
    "setName": "BW Black Star Promos",
    "number": "BW58",
    "rarity": "Promo",
    "artist": "Shin Nagasawa",
    "imageUrl": "https://images.pokemontcg.io/bwp/BW58_hires.png"
  },
  {
    "id": "bwp-BW59",
    "name": "White Kyurem",
    "setName": "BW Black Star Promos",
    "number": "BW59",
    "rarity": "Promo",
    "artist": "Shin Nagasawa",
    "imageUrl": "https://images.pokemontcg.io/bwp/BW59_hires.png"
  },
  {
    "id": "bwp-BW60",
    "name": "Keldeo",
    "setName": "BW Black Star Promos",
    "number": "BW60",
    "rarity": "Promo",
    "artist": "5ban Graphics",
    "imageUrl": "https://images.pokemontcg.io/bwp/BW60_hires.png"
  },
  {
    "id": "bwp-BW61",
    "name": "Keldeo-EX",
    "setName": "BW Black Star Promos",
    "number": "BW61",
    "rarity": "Promo",
    "artist": "Toyste Beach",
    "imageUrl": "https://images.pokemontcg.io/bwp/BW61_hires.png"
  },
  {
    "id": "bwp-BW62",
    "name": "Black Kyurem-EX",
    "setName": "BW Black Star Promos",
    "number": "BW62",
    "rarity": "Promo",
    "artist": "Eske Yoshinob",
    "imageUrl": "https://images.pokemontcg.io/bwp/BW62_hires.png"
  },
  {
    "id": "bwp-BW63",
    "name": "White Kyurem-EX",
    "setName": "BW Black Star Promos",
    "number": "BW63",
    "rarity": "Promo",
    "artist": "Eske Yoshinob",
    "imageUrl": "https://images.pokemontcg.io/bwp/BW63_hires.png"
  },
  {
    "id": "bwp-BW64",
    "name": "Drifblim",
    "setName": "BW Black Star Promos",
    "number": "BW64",
    "rarity": "Promo",
    "artist": "Naoki Saito",
    "imageUrl": "https://images.pokemontcg.io/bwp/BW64_hires.png"
  },
  {
    "id": "bwp-BW65",
    "name": "Jigglypuff",
    "setName": "BW Black Star Promos",
    "number": "BW65",
    "rarity": "Promo",
    "artist": "MAHOU",
    "imageUrl": "https://images.pokemontcg.io/bwp/BW65_hires.png"
  },
  {
    "id": "bwp-BW66",
    "name": "Ninetales",
    "setName": "BW Black Star Promos",
    "number": "BW66",
    "rarity": "Promo",
    "artist": "Hideaki Hakozaki",
    "imageUrl": "https://images.pokemontcg.io/bwp/BW66_hires.png"
  },
  {
    "id": "bwp-BW67",
    "name": "Ampharos",
    "setName": "BW Black Star Promos",
    "number": "BW67",
    "rarity": "Promo",
    "artist": "Naoki Saito",
    "imageUrl": "https://images.pokemontcg.io/bwp/BW67_hires.png"
  },
  {
    "id": "bwp-BW68",
    "name": "Meloetta",
    "setName": "BW Black Star Promos",
    "number": "BW68",
    "rarity": "Promo",
    "artist": "Naoki Saito",
    "imageUrl": "https://images.pokemontcg.io/bwp/BW68_hires.png"
  },
  {
    "id": "bwp-BW69",
    "name": "Meloetta",
    "setName": "BW Black Star Promos",
    "number": "BW69",
    "rarity": "Promo",
    "artist": "Shin Nagasawa",
    "imageUrl": "https://images.pokemontcg.io/bwp/BW69_hires.png"
  },
  {
    "id": "bwp-BW70",
    "name": "Virizion",
    "setName": "BW Black Star Promos",
    "number": "BW70",
    "rarity": "Promo",
    "artist": "5ban Graphics",
    "imageUrl": "https://images.pokemontcg.io/bwp/BW70_hires.png"
  },
  {
    "id": "bwp-BW71",
    "name": "Terrakion",
    "setName": "BW Black Star Promos",
    "number": "BW71",
    "rarity": "Promo",
    "artist": "5ban Graphics",
    "imageUrl": "https://images.pokemontcg.io/bwp/BW71_hires.png"
  },
  {
    "id": "bwp-BW72",
    "name": "Cobalion",
    "setName": "BW Black Star Promos",
    "number": "BW72",
    "rarity": "Promo",
    "artist": "5ban Graphics",
    "imageUrl": "https://images.pokemontcg.io/bwp/BW72_hires.png"
  },
  {
    "id": "bwp-BW73",
    "name": "Darkrai",
    "setName": "BW Black Star Promos",
    "number": "BW73",
    "rarity": "Promo",
    "artist": "5ban Graphics",
    "imageUrl": "https://images.pokemontcg.io/bwp/BW73_hires.png"
  },
  {
    "id": "bwp-BW74",
    "name": "Giratina",
    "setName": "BW Black Star Promos",
    "number": "BW74",
    "rarity": "Promo",
    "artist": "5ban Graphics",
    "imageUrl": "https://images.pokemontcg.io/bwp/BW74_hires.png"
  },
  {
    "id": "bwp-BW75",
    "name": "Metagross",
    "setName": "BW Black Star Promos",
    "number": "BW75",
    "rarity": "Promo",
    "artist": "5ban Graphics",
    "imageUrl": "https://images.pokemontcg.io/bwp/BW75_hires.png"
  },
  {
    "id": "bwp-BW76",
    "name": "Electrode",
    "setName": "BW Black Star Promos",
    "number": "BW76",
    "rarity": "Promo",
    "artist": "5ban Graphics",
    "imageUrl": "https://images.pokemontcg.io/bwp/BW76_hires.png"
  },
  {
    "id": "bwp-BW77",
    "name": "Pikachu",
    "setName": "BW Black Star Promos",
    "number": "BW77",
    "rarity": "Promo",
    "artist": "Mizue",
    "imageUrl": "https://images.pokemontcg.io/bwp/BW77_hires.png"
  },
  {
    "id": "bwp-BW78",
    "name": "Raichu",
    "setName": "BW Black Star Promos",
    "number": "BW78",
    "rarity": "Promo",
    "artist": "Mizue",
    "imageUrl": "https://images.pokemontcg.io/bwp/BW78_hires.png"
  },
  {
    "id": "bwp-BW79",
    "name": "Landorus",
    "setName": "BW Black Star Promos",
    "number": "BW79",
    "rarity": "Promo",
    "artist": "5ban Graphics",
    "imageUrl": "https://images.pokemontcg.io/bwp/BW79_hires.png"
  },
  {
    "id": "bwp-BW80",
    "name": "Druddigon",
    "setName": "BW Black Star Promos",
    "number": "BW80",
    "rarity": "Promo",
    "artist": "5ban Graphics",
    "imageUrl": "https://images.pokemontcg.io/bwp/BW80_hires.png"
  },
  {
    "id": "bwp-BW81",
    "name": "Thundurus-EX",
    "setName": "BW Black Star Promos",
    "number": "BW81",
    "rarity": "Promo",
    "artist": "Eske Yoshinob",
    "imageUrl": "https://images.pokemontcg.io/bwp/BW81_hires.png"
  },
  {
    "id": "bwp-BW82",
    "name": "Deoxys-EX",
    "setName": "BW Black Star Promos",
    "number": "BW82",
    "rarity": "Promo",
    "artist": "Eske Yoshinob",
    "imageUrl": "https://images.pokemontcg.io/bwp/BW82_hires.png"
  },
  {
    "id": "bwp-BW83",
    "name": "Lugia-EX",
    "setName": "BW Black Star Promos",
    "number": "BW83",
    "rarity": "Promo",
    "artist": "Toyste Beach",
    "imageUrl": "https://images.pokemontcg.io/bwp/BW83_hires.png"
  },
  {
    "id": "bwp-BW84",
    "name": "Porygon-Z",
    "setName": "BW Black Star Promos",
    "number": "BW84",
    "rarity": "Promo",
    "artist": "5ban Graphics",
    "imageUrl": "https://images.pokemontcg.io/bwp/BW84_hires.png"
  },
  {
    "id": "bwp-BW85",
    "name": "Lucario",
    "setName": "BW Black Star Promos",
    "number": "BW85",
    "rarity": "Promo",
    "artist": "Masakazu Fukuda",
    "imageUrl": "https://images.pokemontcg.io/bwp/BW85_hires.png"
  },
  {
    "id": "bwp-BW86",
    "name": "Genesect",
    "setName": "BW Black Star Promos",
    "number": "BW86",
    "rarity": "Promo",
    "artist": "5ban Graphics",
    "imageUrl": "https://images.pokemontcg.io/bwp/BW86_hires.png"
  },
  {
    "id": "bwp-BW87",
    "name": "Leafeon",
    "setName": "BW Black Star Promos",
    "number": "BW87",
    "rarity": "Promo",
    "artist": "The Pokémon Company Art Team",
    "imageUrl": "https://images.pokemontcg.io/bwp/BW87_hires.png"
  },
  {
    "id": "bwp-BW88",
    "name": "Flareon",
    "setName": "BW Black Star Promos",
    "number": "BW88",
    "rarity": "Promo",
    "artist": "The Pokémon Company Art Team",
    "imageUrl": "https://images.pokemontcg.io/bwp/BW88_hires.png"
  },
  {
    "id": "bwp-BW89",
    "name": "Vaporeon",
    "setName": "BW Black Star Promos",
    "number": "BW89",
    "rarity": "Promo",
    "artist": "The Pokémon Company Art Team",
    "imageUrl": "https://images.pokemontcg.io/bwp/BW89_hires.png"
  },
  {
    "id": "bwp-BW90",
    "name": "Glaceon",
    "setName": "BW Black Star Promos",
    "number": "BW90",
    "rarity": "Promo",
    "artist": "The Pokémon Company Art Team",
    "imageUrl": "https://images.pokemontcg.io/bwp/BW90_hires.png"
  },
  {
    "id": "bwp-BW91",
    "name": "Jolteon",
    "setName": "BW Black Star Promos",
    "number": "BW91",
    "rarity": "Promo",
    "artist": "The Pokémon Company Art Team",
    "imageUrl": "https://images.pokemontcg.io/bwp/BW91_hires.png"
  },
  {
    "id": "bwp-BW92",
    "name": "Espeon",
    "setName": "BW Black Star Promos",
    "number": "BW92",
    "rarity": "Promo",
    "artist": "The Pokémon Company Art Team",
    "imageUrl": "https://images.pokemontcg.io/bwp/BW92_hires.png"
  },
  {
    "id": "bwp-BW93",
    "name": "Umbreon",
    "setName": "BW Black Star Promos",
    "number": "BW93",
    "rarity": "Promo",
    "artist": "The Pokémon Company Art Team",
    "imageUrl": "https://images.pokemontcg.io/bwp/BW93_hires.png"
  },
  {
    "id": "bwp-BW94",
    "name": "Eevee",
    "setName": "BW Black Star Promos",
    "number": "BW94",
    "rarity": "Promo",
    "artist": "The Pokémon Company Art Team",
    "imageUrl": "https://images.pokemontcg.io/bwp/BW94_hires.png"
  },
  {
    "id": "bwp-BW95",
    "name": "Champions Festival",
    "setName": "BW Black Star Promos",
    "number": "BW95",
    "rarity": "Promo",
    "artist": "Naoki Saito",
    "imageUrl": "https://images.pokemontcg.io/bwp/BW95_hires.png"
  },
  {
    "id": "bwp-BW96",
    "name": "Tornadus-EX",
    "setName": "BW Black Star Promos",
    "number": "BW96",
    "rarity": "Promo",
    "artist": "Ryo Ueda",
    "imageUrl": "https://images.pokemontcg.io/bwp/BW96_hires.png"
  },
  {
    "id": "bwp-BW97",
    "name": "Eevee",
    "setName": "BW Black Star Promos",
    "number": "BW97",
    "rarity": "Promo",
    "artist": "Akira Komayama",
    "imageUrl": "https://images.pokemontcg.io/bwp/BW97_hires.png"
  },
  {
    "id": "bwp-BW98",
    "name": "Mew",
    "setName": "BW Black Star Promos",
    "number": "BW98",
    "rarity": "Promo",
    "artist": "Naoki Saito",
    "imageUrl": "https://images.pokemontcg.io/bwp/BW98_hires.png"
  },
  {
    "id": "bwp-BW99",
    "name": "Genesect",
    "setName": "BW Black Star Promos",
    "number": "BW99",
    "rarity": "Promo",
    "artist": "5ban Graphics",
    "imageUrl": "https://images.pokemontcg.io/bwp/BW99_hires.png"
  },
  {
    "id": "bwp-BW100",
    "name": "N",
    "setName": "BW Black Star Promos",
    "number": "BW100",
    "rarity": "Promo",
    "artist": "Yusuke Ohmura",
    "imageUrl": "https://images.pokemontcg.io/bwp/BW100_hires.png"
  },
  {
    "id": "bwp-BW101",
    "name": "Genesect",
    "setName": "BW Black Star Promos",
    "number": "BW101",
    "rarity": "Promo",
    "artist": "5ban Graphics",
    "imageUrl": "https://images.pokemontcg.io/bwp/BW101_hires.png"
  }
]
