[
  {
    "id": "det1-1",
    "name": "Bulbasaur",
    "setName": "Detective Pikachu",
    "number": "1",
    "rarity": "Common",
    "artist": "MPC Film",
    "imageUrl": "https://images.pokemontcg.io/det1/1_hires.png"
  },
  {
    "id": "det1-2",
    "name": "Ludicolo",
    "setName": "Detective Pikachu",
    "number": "2",
    "rarity": "Rare",
    "artist": "Framestore",
    "imageUrl": "https://images.pokemontcg.io/det1/2_hires.png"
  },
  {
    "id": "det1-3",
    "name": "Morelull",
    "setName": "Detective Pikachu",
    "number": "3",
    "rarity": "Common",
    "artist": "MPC Film",
    "imageUrl": "https://images.pokemontcg.io/det1/3_hires.png"
  },
  {
    "id": "det1-4",
    "name": "Charmander",
    "setName": "Detective Pikachu",
    "number": "4",
    "rarity": "Common",
    "artist": "MPC Film",
    "imageUrl": "https://images.pokemontcg.io/det1/4_hires.png"
  },
  {
    "id": "det1-5",
    "name": "Charizard",
    "setName": "Detective Pikachu",
    "number": "5",
    "rarity": "Rare Ultra",
    "artist": "Framestore",
    "imageUrl": "https://images.pokemontcg.io/det1/5_hires.png"
  },
  {
    "id": "det1-6",
    "name": "Arcanine",
    "setName": "Detective Pikachu",
    "number": "6",
    "rarity": "Rare",
    "artist": "MPC Film",
    "imageUrl": "https://images.pokemontcg.io/det1/6_hires.png"
  },
  {
    "id": "det1-7",
    "name": "Psyduck",
    "setName": "Detective Pikachu",
    "number": "7",
    "rarity": "Common",
    "artist": "Framestore",
    "imageUrl": "https://images.pokemontcg.io/det1/7_hires.png"
  },
  {
    "id": "det1-8",
    "name": "Magikarp",
    "setName": "Detective Pikachu",
    "number": "8",
    "rarity": "Common",
    "artist": "Framestore",
    "imageUrl": "https://images.pokemontcg.io/det1/8_hires.png"
  },
  {
    "id": "det1-9",
    "name": "Greninja",
    "setName": "Detective Pikachu",
    "number": "9",
    "rarity": "Rare Ultra",
    "artist": "MPC Film",
    "imageUrl": "https://images.pokemontcg.io/det1/9_hires.png"
  },
  {
    "id": "det1-10",
    "name": "Detective Pikachu",
    "setName": "Detective Pikachu",
    "number": "10",
    "rarity": "Rare",
    "artist": "MPC Film",
    "imageUrl": "https://images.pokemontcg.io/det1/10_hires.png"
  },
  {
    "id": "det1-11",
    "name": "Mr. Mime",
    "setName": "Detective Pikachu",
    "number": "11",
    "rarity": "Rare",
    "artist": "MPC Film",
    "imageUrl": "https://images.pokemontcg.io/det1/11_hires.png"
  },
  {
    "id": "det1-12",
    "name": "Mewtwo",
    "setName": "Detective Pikachu",
    "number": "12",
    "rarity": "Rare Ultra",
    "artist": "MPC Film",
    "imageUrl": "https://images.pokemontcg.io/det1/12_hires.png"
  },
  {
    "id": "det1-13",
    "name": "Machamp",
    "setName": "Detective Pikachu",
    "number": "13",
    "rarity": "Rare",
    "artist": "MPC Film",
    "imageUrl": "https://images.pokemontcg.io/det1/13_hires.png"
  },
  {
    "id": "det1-14",
    "name": "Jigglypuff",
    "setName": "Detective Pikachu",
    "number": "14",
    "rarity": "Common",
    "artist": "Framestore",
    "imageUrl": "https://images.pokemontcg.io/det1/14_hires.png"
  },
  {
    "id": "det1-15",
    "name": "Snubbull",
    "setName": "Detective Pikachu",
    "number": "15",
    "rarity": "Common",
    "artist": "Framestore",
    "imageUrl": "https://images.pokemontcg.io/det1/15_hires.png"
  },
  {
    "id": "det1-16",
    "name": "Lickitung",
    "setName": "Detective Pikachu",
    "number": "16",
    "rarity": "Common",
    "artist": "MPC Film",
    "imageUrl": "https://images.pokemontcg.io/det1/16_hires.png"
  },
  {
    "id": "det1-17",
    "name": "Ditto",
    "setName": "Detective Pikachu",
    "number": "17",
    "rarity": "Rare Ultra",
    "artist": "MPC Film",
    "imageUrl": "https://images.pokemontcg.io/det1/17_hires.png"
  },
  {
    "id": "det1-18",
    "name": "Slaking",
    "setName": "Detective Pikachu",
    "number": "18",
    "rarity": "Rare",
    "artist": "Framestore",
    "imageUrl": "https://images.pokemontcg.io/det1/18_hires.png"
  }
]
