[
  {
    "id": "pop2-1",
    "name": "Entei",
    "setName": "POP Series 2",
    "number": "1",
    "rarity": "Rare",
    "artist": "Kouki Saitou",
    "imageUrl": "https://images.pokemontcg.io/pop2/1_hires.png"
  },
  {
    "id": "pop2-2",
    "name": "Pidgeot",
    "setName": "POP Series 2",
    "number": "2",
    "rarity": "Rare",
    "artist": "Ken Sugimori",
    "imageUrl": "https://images.pokemontcg.io/pop2/2_hires.png"
  },
  {
    "id": "pop2-3",
    "name": "Raikou",
    "setName": "POP Series 2",
    "number": "3",
    "rarity": "Rare",
    "artist": "Kouki Saitou",
    "imageUrl": "https://images.pokemontcg.io/pop2/3_hires.png"
  },
  {
    "id": "pop2-4",
    "name": "Suicune",
    "setName": "POP Series 2",
    "number": "4",
    "rarity": "Rare",
    "artist": "Kouki Saitou",
    "imageUrl": "https://images.pokemontcg.io/pop2/4_hires.png"
  },
  {
    "id": "pop2-5",
    "name": "Tauros",
    "setName": "POP Series 2",
    "number": "5",
    "rarity": "Rare",
    "artist": "Kouki Saitou",
    "imageUrl": "https://images.pokemontcg.io/pop2/5_hires.png"
  },
  {
    "id": "pop2-6",
    "name": "Venusaur",
    "setName": "POP Series 2",
    "number": "6",
    "rarity": "Rare",
    "artist": "Mitsuhiro Arita",
    "imageUrl": "https://images.pokemontcg.io/pop2/6_hires.png"
  },
  {
    "id": "pop2-7",
    "name": "Ivysaur",
    "setName": "POP Series 2",
    "number": "7",
    "rarity": "Uncommon",
    "artist": "Ken Sugimori",
    "imageUrl": "https://images.pokemontcg.io/pop2/7_hires.png"
  },
  {
    "id": "pop2-8",
    "name": "Mr. Briney's Compassion",
    "setName": "POP Series 2",
    "number": "8",
    "rarity": "Uncommon",
    "artist": "Ken Sugimori",
    "imageUrl": "https://images.pokemontcg.io/pop2/8_hires.png"
  },
  {
    "id": "pop2-9",
    "name": "Multi Technical Machine 01",
    "setName": "POP Series 2",
    "number": "9",
    "rarity": "Uncommon",
    "artist": "\"Big Mama\" Tagawa",
    "imageUrl": "https://images.pokemontcg.io/pop2/9_hires.png"
  },
  {
    "id": "pop2-10",
    "name": "Pokémon Park",
    "setName": "POP Series 2",
    "number": "10",
    "rarity": "Uncommon",
    "artist": "Kazuo Yazawa",
    "imageUrl": "https://images.pokemontcg.io/pop2/10_hires.png"
  },
  {
    "id": "pop2-11",
    "name": "TV Reporter",
    "setName": "POP Series 2",
    "number": "11",
    "rarity": "Uncommon",
    "artist": "Ken Sugimori",
    "imageUrl": "https://images.pokemontcg.io/pop2/11_hires.png"
  },
  {
    "id": "pop2-12",
    "name": "Bulbasaur",
    "setName": "POP Series 2",
    "number": "12",
    "rarity": "Common",
    "artist": "Midori Harada",
    "imageUrl": "https://images.pokemontcg.io/pop2/12_hires.png"
  },
  {
    "id": "pop2-13",
    "name": "Cacnea",
    "setName": "POP Series 2",
    "number": "13",
    "rarity": "Common",
    "artist": "Ken Sugimori",
    "imageUrl": "https://images.pokemontcg.io/pop2/13_hires.png"
  },
  {
    "id": "pop2-14",
    "name": "Luvdisc",
    "setName": "POP Series 2",
    "number": "14",
    "rarity": "Common",
    "artist": "Atsuko Nishida",
    "imageUrl": "https://images.pokemontcg.io/pop2/14_hires.png"
  },
  {
    "id": "pop2-15",
    "name": "Phanpy",
    "setName": "POP Series 2",
    "number": "15",
    "rarity": "Common",
    "artist": "Tomokazu Komiya",
    "imageUrl": "https://images.pokemontcg.io/pop2/15_hires.png"
  },
  {
    "id": "pop2-16",
    "name": "Pikachu",
    "setName": "POP Series 2",
    "number": "16",
    "rarity": "Common",
    "artist": "Yuka Morii",
    "imageUrl": "https://images.pokemontcg.io/pop2/16_hires.png"
  },
  {
    "id": "pop2-17",
    "name": "Celebi ex",
    "setName": "POP Series 2",
    "number": "17",
    "rarity": "Rare",
    "artist": "Ryo Ueda",
    "imageUrl": "https://images.pokemontcg.io/pop2/17_hires.png"
  }
]
